ep_wifi.py
micropython_eydam_prototyping_wifi-0.0.1.dist-info/LICENSE
micropython_eydam_prototyping_wifi-0.0.1.dist-info/METADATA
micropython_eydam_prototyping_wifi-0.0.1.dist-info/WHEEL
micropython_eydam_prototyping_wifi-0.0.1.dist-info/top_level.txt
micropython_eydam_prototyping_wifi-0.0.1.dist-info/RECORD
