Metadata-Version: 2.1
Name: micropython-eydam-prototyping-wifi
Version: 0.0.1
Summary: Some wifi functions for MicroPython
Home-page: https://github.com/eydam-prototyping/tutorials_de/blob/master/micropython/packages/ep_wifi
Author: Tobias Eydam
Author-email: eydam-prototyping@outlook.com
License: UNKNOWN
Platform: UNKNOWN
Classifier: Programming Language :: Python :: Implementation :: MicroPython
Classifier: License :: OSI Approved :: MIT License
Classifier: Operating System :: OS Independent
